NamasteigNewLatest/__init__.py
NamasteigNewLatest/login.py
NamasteigNewLatest-0.0.1.dist-info/LICENSE
NamasteigNewLatest-0.0.1.dist-info/METADATA
NamasteigNewLatest-0.0.1.dist-info/WHEEL
NamasteigNewLatest-0.0.1.dist-info/top_level.txt
NamasteigNewLatest-0.0.1.dist-info/RECORD
